allstar/__init__.py
allstar/__main__.py
allstar/star.py
allstar-1.1.6.dist-info/LICENSE
allstar-1.1.6.dist-info/METADATA
allstar-1.1.6.dist-info/WHEEL
allstar-1.1.6.dist-info/top_level.txt
allstar-1.1.6.dist-info/RECORD
