Metadata-Version: 2.1
Name: allstar
Version: 1.1.6
Summary: A Python manager for the modules __all__ variable.
Author-email: Virtual Items <virtualitemsuniverse@gmail.com>
Project-URL: Homepage, https://github.com/virtualitems/allstar
Project-URL: Bug Tracker, https://github.com/virtualitems/allstar/issues
Classifier: Programming Language :: Python :: 3
Classifier: License :: OSI Approved :: MIT License
Classifier: Operating System :: OS Independent
Requires-Python: >=3.7
License-File: LICENSE
